{"p":"\u5e6b","ph":"\u6ec2","b":"\u4e26","m":"\u660e","t":"\u7aef","th":"\u900f","d":"\u5b9a","n":"\u6ce5","tr":"\u77e5","thr":"\u5fb9","dr":"\u6f84","nr":"\u5a18","l":"\u4f86","c":"\u7cbe","ch":"\u6e05","z":"\u5f9e","s":"\u5fc3","zs":"\u90aa","cr":"\u838a","chr":"\u521d","zr":"\u5d07","sr":"\u751f","zsr":"\u4fdf","cj":"\u7ae0","chj":"\u660c","zj":"\u5e38","sj":"\u66f8","zsj":"\u8239","nj":"\u65e5","k":"\u898b","kh":"\u8c3f","g":"\u7fa3","ng":"\u7591","h":"\u66c9","gh":"\u5323","q":"\u5f71","":"\u4e91","j":"\u4ee5"}